{"id":"40C82A0D-F6AC-4D18-9E85-B3DBDD069EDB","validationEntity":{"analysedDataType":"auto","dataResult":{"createdDate":"2022-07-20T11:51:11Z"}},"modelEntity":{"createdDate":"2022-07-20T11:51:06Z","id":"B4F8B899-4FA4-48D9-88C5-7859DC572469","experimentID":"40C82A0D-F6AC-4D18-9E85-B3DBDD069EDB","title":"","modifiedDate":"2022-07-20T11:51:06Z","preferredFilename":"","version":"1.0","modelURL":"Models\/BetterRest%201.mlmodel"},"version":"1.0","settingEntity":{"augmentations":[],"suggestedColumns":["wake","estimatedSleep","coffee","actualSleep"],"targetColumn":"actualSleep","seedType":"default","transferLearningEmbeddingType":"dynamic","handPoseClassifierAugmentations":[],"featureNames":["wake","estimatedSleep","coffee"],"algorithmType":"maxEnt","harVideoAugmentations":0,"taskType":"generalRegresor","suggestedColumnValues":["31.500, 32.400, 26.100, 40.500, 19.800, 27.000, 20.700, 21.600, 41.400, 34.200, 21.600, 78.300, 32.400, 28.800, 18.900, 18.000, 28.800, 18.000, 7.200, 35.100, 24.300, 35.100, 34.200, 27.900, 30.600, 69.300, 35.100, 34.200, 34.200, 23.400","9,00, 5,00, 6,50, 8,75, 6,00, 7,50, 9,25, 6,00, 9,25, 6,75, 5,25, 9,25, 10,00, 8,75, 8,25, 6,25, 10,00, 6,25, 10,00, 9,50, 5,00, 7,50, 6,25, 8,00, 8,00, 6,50, 8,00, 10,00, 8,25, 8,00","6, 2, 10, 4, 3, 1, 1, 3, 5, 8, 3, 8, 2, 3, 1, 2, 3, 2, 1, 4, 2, 1, 1, 4, 3, 7, 4, 4, 1, 3","38.230, 20.180, 31.989, 35.258, 24.487, 28.300, 34.548, 24.557, 37.836, 31.340, 21.874, 40.405, 38.076, 34.265, 30.936, 24.665, 39.007, 24.578, 37.267, 37.878, 20.220, 28.400, 23.882, 32.427, 31.699, 29.670, 32.789, 39.792, 30.935, 31.701"],"handActionClassifierAugmentations":[],"suggestedColumnTypes":["Int","Double","Int","Int"],"styleTransferAlgorithmType":"image","generalRegressorType":{"auto":{}}},"state":"trained","trainingEntity":{"finishTime":"2022-07-20T11:51:30Z","recipeTrainingResults":{"generalRegressor":{"maximumError":701.80460036647855,"rootMeanSquaredError":176.77894789980814}},"dataResult":{"itemsCount":10000,"createdDate":"2022-07-20T11:51:11Z","dataURL":"file:\/\/\/Users\/silviupreoteasa\/Downloads\/HackingWithSwift-main\/SwiftUI\/project4-files\/BetterRest.csv","columnTypes":["Int","Double","Int","Int"],"analysis":{"summary":{"canUseValidation":1,"sampleCount":10000},"issues":[{"description":"Data has 10000 rows","severity":"info"}],"regressorAnalysis":{"targetRange":[19216,45224]}},"dataSourceID":"6DB65284-3AA7-4E36-8169-30C82612F5E9","columns":["wake","estimatedSleep","coffee","actualSleep"],"columnValues":["31.500, 32.400, 26.100, 40.500, 19.800, 27.000, 20.700, 21.600, 41.400, 34.200, 21.600, 78.300, 32.400, 28.800, 18.900, 18.000, 28.800, 18.000, 7.200, 35.100, 24.300, 35.100, 34.200, 27.900, 30.600, 69.300, 35.100, 34.200, 34.200, 23.400","9,00, 5,00, 6,50, 8,75, 6,00, 7,50, 9,25, 6,00, 9,25, 6,75, 5,25, 9,25, 10,00, 8,75, 8,25, 6,25, 10,00, 6,25, 10,00, 9,50, 5,00, 7,50, 6,25, 8,00, 8,00, 6,50, 8,00, 10,00, 8,25, 8,00","6, 2, 10, 4, 3, 1, 1, 3, 5, 8, 3, 8, 2, 3, 1, 2, 3, 2, 1, 4, 2, 1, 1, 4, 3, 7, 4, 4, 1, 3","38.230, 20.180, 31.989, 35.258, 24.487, 28.300, 34.548, 24.557, 37.836, 31.340, 21.874, 40.405, 38.076, 34.265, 30.936, 24.665, 39.007, 24.578, 37.267, 37.878, 20.220, 28.400, 23.882, 32.427, 31.699, 29.670, 32.789, 39.792, 30.935, 31.701"],"targetRange":[19216,45224]},"dataURL":"file:\/\/\/Users\/silviupreoteasa\/Downloads\/HackingWithSwift-main\/SwiftUI\/project4-files\/BetterRest.csv","featureExtractionCheckpointMayBeAvailable":false,"recipeValidationResults":{"generalRegressor":{"maximumError":666.65537722926092,"rootMeanSquaredError":182.17248501288037}},"progress":[],"trainingAccuracy":176.77894789980814,"checkpointMetrics":{},"analysedDataType":"none","dataSourceID":"6DB65284-3AA7-4E36-8169-30C82612F5E9","snapshottableCheckpoints":{},"validationAccuracy":182.17248501288037,"startTime":"2022-07-20T11:51:29Z"},"createdDate":"2022-07-20T11:51:06Z","evaluationContainerEntity":{"testingEvaluationEntity":{"id":"f3c831f6-7636-4349-8443-57188d98feaf","createdDate":"2022-07-20T11:51:06Z","dataResult":{"createdDate":"2022-07-20T11:51:11Z"},"analysedDataType":"none"},"createdDate":"2022-07-20T11:52:09Z","id":"561e15c2-4c50-4ea9-938a-fba21852bef5","trainingEvaluationEntity":{"result":{"generalRegressor":{"maximumError":701.80460036647855,"rootMeanSquaredError":176.77894789980814}},"createdDate":"2022-07-20T11:51:06Z","id":"1f267aab-f3f3-40e4-8fc4-c8dea4fecd51","dataURL":"file:\/\/\/Users\/silviupreoteasa\/Downloads\/HackingWithSwift-main\/SwiftUI\/project4-files\/BetterRest.csv","dataSourceID":"6DB65284-3AA7-4E36-8169-30C82612F5E9","dataResult":{"itemsCount":10000,"createdDate":"2022-07-20T11:51:11Z","targetRange":[19216,45224],"dataURL":"file:\/\/\/Users\/silviupreoteasa\/Downloads\/HackingWithSwift-main\/SwiftUI\/project4-files\/BetterRest.csv","dataSourceID":"6DB65284-3AA7-4E36-8169-30C82612F5E9","analysis":{"summary":{"canUseValidation":1,"sampleCount":10000},"issues":[{"description":"Data has 10000 rows","severity":"info"}],"regressorAnalysis":{"targetRange":[19216,45224]}}},"analysedDataType":"none"},"previewType":"tabularRegressor","modifiedDate":"2022-07-20T11:52:09Z","validationEvaluationEntity":{"result":{"generalRegressor":{"maximumError":666.65537722926092,"rootMeanSquaredError":182.17248501288037}},"id":"41db97db-3bbd-4153-82cb-d0ff716dcde5","createdDate":"2022-07-20T11:51:06Z","dataResult":{"createdDate":"2022-07-20T11:51:11Z"},"analysedDataType":"auto"},"evaluationEntities":[{"id":"a66dbb7c-a63d-4ed7-91f9-1ddca0a680de","createdDate":"2022-07-20T11:52:09Z","dataResult":{},"analysedDataType":"none"}]},"evaluationEntities":[],"activityEntities":["experimentCreated",[{"id":"3C24EAF6-B2CF-4D1A-B610-95522FC3CC1A","title":"Model Source Created","createdDate":"2022-07-20T11:51:06Z","event":"experimentCreated","subtitle":"BetterRest 1"}],"trainingStarted",[{"id":"D5385504-564B-4477-9F92-826E5E346B5D","title":"Training Started","createdDate":"2022-07-20T11:51:29Z","event":"trainingStarted","subtitle":"BetterRest 1"}],"trainingFinished",[{"id":"7FA9461E-C7A4-47DB-988D-F0C9CA69049A","title":"Training Completed","createdDate":"2022-07-20T11:51:30Z","event":"trainingFinished","subtitle":"BetterRest 1"}],"trainingDataAdded",[{"id":"F0D10A2B-99EF-446D-AAA2-A289F7F8FC18","title":"Training Data Added","createdDate":"2022-07-20T11:51:11Z","event":"trainingDataAdded","subtitle":"BetterRest.csv"}]],"title":"BetterRest 1","evaluationEntity":{"id":"61cbc02d-68e5-4c1d-98dd-44bd24c18d1c","createdDate":"2022-07-20T11:51:06Z","dataResult":{"createdDate":"2022-07-20T11:51:11Z"},"analysedDataType":"none"},"evaluationState":"uninitialized","snapshotRole":{"withoutSnapshots":0},"modifiedDate":"2022-07-20T11:52:09Z","contentDataResult":{"createdDate":"2022-07-20T11:51:11Z"},"preferredFilename":"BetterRest 1"}